{
  "dataset": "scifact",
  "nodes": 10000,
  "seed": 20235956,
  "k_query": 300,
  "meta_anchors": 1,
  "random_routing": true,
  "local_topk": 30,
  "use_pq": true,
  "n_query": 100,
  "reachable_hit5": 95.0,
  "returned_hit5": 95.0,
  "final_hit5": 95.0,
  "reachable_recall5": 55.99999999999999,
  "returned_recall5": 55.99999999999999,
  "recall5": 53.8,
  "recall10": 54.5,
  "mean_unique_candidates": 2130.59,
  "mean_nodes_touched": 1500.0,
  "pct_network_touched": 15.0,
  "metadata_total": 25894,
  "metadata_mean_per_node": 2.5894,
  "metadata_gini": 0.9054185062176566
}